ShellyPool/ShellyAppliance.py
ShellyPool/ShellyButton.py
ShellyPool/ShellyConfig.py
ShellyPool/ShellyHTSensor.py
ShellyPool/ShellyPlugS.py
ShellyPool/__init__.py
ShellyPool/const.py
shellypool-0.1.1.dist-info/WHEEL
shellypool-0.1.1.dist-info/METADATA
shellypool-0.1.1.dist-info/RECORD
